LeBotTel/__init__.py
LeBotTel/base_message_handler.py
LeBotTel/base_telegram_bot.py
LeBotTel/exceptions.py
LeBotTel-0.4.2.dist-info/LICENSE
LeBotTel-0.4.2.dist-info/METADATA
LeBotTel-0.4.2.dist-info/WHEEL
LeBotTel-0.4.2.dist-info/top_level.txt
LeBotTel-0.4.2.dist-info/RECORD
