Metadata-Version: 2.1
Name: LeBotTel
Version: 0.4.2
Author: Antonio Vidos, Tobias Lettner, Tobias Weiß, Uwe Kölbl
Author-email: lebottel.team@gmail.com
License: MIT License
Classifier: Programming Language :: Python :: 3
Classifier: License :: OSI Approved :: MIT License
Classifier: Operating System :: OS Independent
Requires-Python: >=3.10.0
License-File: LICENSE
Requires-Dist: requests~=2.31.0
Provides-Extra: test
Requires-Dist: pytest~=7.4.3; extra == "test"
Requires-Dist: requests_mock~=1.11.0; extra == "test"
Provides-Extra: lint
Requires-Dist: ruff==0.7.4; extra == "lint"
Provides-Extra: dev
Requires-Dist: LeBotTel[lint,test]; extra == "dev"
